{
	"env_name": "IndustrialArea",
	"env_bin": "E:\\gym_unrealcv2.0\\gym-unrealcv\\gym_unrealcv\\envs\\UnrealEnv\\Collection_WinNoEditor\\WindowsNoEditor\\Collection\\Binaries\\Win64\\Collection.exe",
	"cam_id": 1,
	"height": 40,
	"pitch": 0,
	"maxsteps": 2000,
	"trigger_th": 0.6,
	"reward_th": 0.1,
	"reward_factor": 10,
	"collision_th": 50,
	"waypoint_th": 200,
	"player": "bp_character_2",
	"targets": {
		"Point": ["SM_Cardboard_Box6_76"]
	},
	"reset_area":[-2232,-1252,-754, -195, 100, 150],
	"test_xy": [
		[-106.195,   437.424],
		[  27.897,  -162.437],
		[  10.832,   135.126],
		[  67.903,    26.995],
		[ -23.558,  -187.354],
		[ -80.312,   254.579]
	],
	"discrete_actions": [
		[0,   200, 0,0],
		[0,  -200, 0,0],
		[15, 50, 0,0],
		[-15,  50, 0,0],
		[0,0, 1, 0],
		[0,0, 0, 1],
		[0,0,0,0]
	],
	"continous_actions": {
		"high": [100,   45, 1],
		"low":  [  0,  -45, 0]
	}
}